{"Ano":2018,"CAR":"SP-3556008-E74686AAD97546FFA4CB6021D6B7997B","Status":"Shapefile SiCAR Processado","SITUACAO":"AT","CONDICAO":"Revisado, aguardando aceite pelo propriet\u00e1rio","Area_Fazenda_Total":459.22,"Area_Fazenda_Florestada":16.04,"APP_Total":28.19,"APP_Florestada":8.02,"RESERVA_LEGAL_Total":91.89,"RESERVA_LEGAL_Florestada":15.38,"VEGETACAO_NATIVA_Total":64,"VEGETACAO_NATIVA_Florestada":7.36,"SERVIDAO_ADMINISTRATIVA_Total":"NaN","SERVIDAO_ADMINISTRATIVA_Florestada":"NaN","USO_RESTRITO_Total":"NaN","USO_RESTRITO_Florestada":"NaN","AREA_CONSOLIDADA_Total":0.14,"AREA_CONSOLIDADA_Florestada":0.06,"A1":0.4,"A2":0.3,"A3":0,"A4":0,"A5":19.76,"A6":7.72,"A7":0,"V11":0.4,"V12":19.76,"V21":0.3,"V22":0,"V23":7.72,"V31":0.4,"V32":8.02}
