{"Ano":2014,"CAR":"MG-3127107-023C43B1C60F4527A0FC38D94AA999C6","Status":"Shapefile SiCAR Processado","SITUACAO":"AT","CONDICAO":"Aguardando analise","Area_Fazenda_Total":66.51,"Area_Fazenda_Florestada":1.65,"APP_Total":0.72,"APP_Florestada":0.72,"RESERVA_LEGAL_Total":1.29,"RESERVA_LEGAL_Florestada":1.28,"VEGETACAO_NATIVA_Total":1.3,"VEGETACAO_NATIVA_Florestada":1.28,"SERVIDAO_ADMINISTRATIVA_Total":"NaN","SERVIDAO_ADMINISTRATIVA_Florestada":"NaN","USO_RESTRITO_Total":"NaN","USO_RESTRITO_Florestada":"NaN","AREA_CONSOLIDADA_Total":65.15,"AREA_CONSOLIDADA_Florestada":0.31,"A1":0,"A2":0.7,"A3":0.01,"A4":0.58,"A5":0,"A6":0.01,"A7":0,"V11":0,"V12":0,"V21":0.7,"V22":0.58,"V23":0.01,"V31":0,"V32":1.3}
