{"Ano":2014,"CAR":"SP-3524303-D78A85C41DBA40D891D0FEA45835EF2D","Status":"Shapefile SiCAR Processado","SITUACAO":"AT","CONDICAO":"Revisado, aguardando aceite pelo propriet\u00e1rio","Area_Fazenda_Total":342.01,"Area_Fazenda_Florestada":12.16,"APP_Total":20.18,"APP_Florestada":9.36,"RESERVA_LEGAL_Total":38.56,"RESERVA_LEGAL_Florestada":10.87,"VEGETACAO_NATIVA_Total":40.4,"VEGETACAO_NATIVA_Florestada":11.82,"SERVIDAO_ADMINISTRATIVA_Total":"NaN","SERVIDAO_ADMINISTRATIVA_Florestada":"NaN","USO_RESTRITO_Total":"NaN","USO_RESTRITO_Florestada":"NaN","AREA_CONSOLIDADA_Total":0.01,"AREA_CONSOLIDADA_Florestada":0,"A1":10.25,"A2":9.31,"A3":18.33,"A4":2.51,"A5":0.57,"A6":0.05,"A7":0,"V11":10.25,"V12":0.57,"V21":9.31,"V22":2.51,"V23":0.05,"V31":10.25,"V32":11.86}
