{"Ano":2014,"CAR":"SP-3524303-A7682ED563804138AF6A3F96D16FA05F","Status":"Shapefile SiCAR Processado","SITUACAO":"AT","CONDICAO":"Aguardando an\u00e1lise, n\u00e3o pass\u00edvel de revis\u00e3o de dados","Area_Fazenda_Total":33.62,"Area_Fazenda_Florestada":0,"APP_Total":1.23,"APP_Florestada":0,"RESERVA_LEGAL_Total":1.61,"RESERVA_LEGAL_Florestada":0,"VEGETACAO_NATIVA_Total":1.61,"VEGETACAO_NATIVA_Florestada":0,"SERVIDAO_ADMINISTRATIVA_Total":"NaN","SERVIDAO_ADMINISTRATIVA_Florestada":"NaN","USO_RESTRITO_Total":"NaN","USO_RESTRITO_Florestada":"NaN","AREA_CONSOLIDADA_Total":32,"AREA_CONSOLIDADA_Florestada":0,"A1":1.22,"A2":0,"A3":0.39,"A4":0,"A5":0.01,"A6":0,"A7":0,"V11":1.22,"V12":0.01,"V21":0,"V22":0,"V23":0,"V31":1.22,"V32":0}
