{"Ano":2023,"CAR":"SP-3529302-DB8A9F86BA3443469E09F7F6F0F560A5","Status":"Shapefile SiCAR Processado","SITUACAO":"AT","CONDICAO":"Revisado, aguardando aceite pelo propriet\u00e1rio","Area_Fazenda_Total":364.03,"Area_Fazenda_Florestada":43.82,"APP_Total":13.49,"APP_Florestada":10.97,"RESERVA_LEGAL_Total":54.26,"RESERVA_LEGAL_Florestada":41.28,"VEGETACAO_NATIVA_Total":51.81,"VEGETACAO_NATIVA_Florestada":39.21,"SERVIDAO_ADMINISTRATIVA_Total":"NaN","SERVIDAO_ADMINISTRATIVA_Florestada":"NaN","USO_RESTRITO_Total":"NaN","USO_RESTRITO_Florestada":"NaN","AREA_CONSOLIDADA_Total":0.06,"AREA_CONSOLIDADA_Florestada":0,"A1":2.48,"A2":9.42,"A3":10.12,"A4":29.79,"A5":0.03,"A6":1.56,"A7":0,"V11":2.48,"V12":0.03,"V21":9.42,"V22":29.79,"V23":1.56,"V31":2.48,"V32":40.76}
