{"Ano":2008,"CAR":"MG-3169604-8085AD3666DB4278969E03CD65B5246F","Status":"Shapefile SiCAR Processado","SITUACAO":"AT","CONDICAO":"Aguardando analise","Area_Fazenda_Total":77.68,"Area_Fazenda_Florestada":4.35,"APP_Total":6.55,"APP_Florestada":0.92,"RESERVA_LEGAL_Total":24.58,"RESERVA_LEGAL_Florestada":4.24,"VEGETACAO_NATIVA_Total":24.8,"VEGETACAO_NATIVA_Florestada":4.35,"SERVIDAO_ADMINISTRATIVA_Total":"NaN","SERVIDAO_ADMINISTRATIVA_Florestada":"NaN","USO_RESTRITO_Total":"NaN","USO_RESTRITO_Florestada":"NaN","AREA_CONSOLIDADA_Total":54.51,"AREA_CONSOLIDADA_Florestada":0,"A1":5.1,"A2":0.92,"A3":14.77,"A4":3.43,"A5":0.53,"A6":0,"A7":0,"V11":5.1,"V12":0.53,"V21":0.92,"V22":3.43,"V23":0,"V31":5.1,"V32":4.35}
