{"Ano":2017,"CAR":"SP-3518602-B30555888C3341CE961D32239F22FE85","Status":"Shapefile SiCAR Processado","SITUACAO":"AT","CONDICAO":"Aguardando an\u00e1lise, n\u00e3o pass\u00edvel de revis\u00e3o de dados","Area_Fazenda_Total":361.65,"Area_Fazenda_Florestada":3.3,"APP_Total":14.61,"APP_Florestada":2.11,"RESERVA_LEGAL_Total":23.94,"RESERVA_LEGAL_Florestada":3.16,"VEGETACAO_NATIVA_Total":23.94,"VEGETACAO_NATIVA_Florestada":3.16,"SERVIDAO_ADMINISTRATIVA_Total":"NaN","SERVIDAO_ADMINISTRATIVA_Florestada":"NaN","USO_RESTRITO_Total":"NaN","USO_RESTRITO_Florestada":"NaN","AREA_CONSOLIDADA_Total":337.64,"AREA_CONSOLIDADA_Florestada":0.13,"A1":11.69,"A2":2.1,"A3":9.09,"A4":1.05,"A5":0.81,"A6":0.01,"A7":0,"V11":11.69,"V12":0.81,"V21":2.1,"V22":1.05,"V23":0.01,"V31":11.69,"V32":3.16}
